ncr/__init__.py
ncr/replace_corefs.py
nested_coref_resolver-0.0.2.dist-info/LICENSE
nested_coref_resolver-0.0.2.dist-info/METADATA
nested_coref_resolver-0.0.2.dist-info/WHEEL
nested_coref_resolver-0.0.2.dist-info/top_level.txt
nested_coref_resolver-0.0.2.dist-info/RECORD
