Metadata-Version: 2.1
Name: nested-coref-resolver
Version: 0.0.2
Summary: light-weight python script to transform documents by replacing all mentions of co-referent clusters with first non-pronominal mention. Importantly, it explicitly handles nested coreferent mentions.
Home-page: https://github.com/griff4692/resolve_coref_clusters
Author: Griffin Adams
Author-email: griffin.adams@columbia.edu
License: UNKNOWN
Platform: UNKNOWN
Classifier: Programming Language :: Python :: 3
Classifier: License :: OSI Approved :: MIT License
Classifier: Operating System :: OS Independent
Requires-Python: >=2.6
